{"content":[{"id":"1ba167d2","settings":{"layout":"full_width","margin":{"unit":"%","top":"","right":"","bottom":"","left":"","isLinked":true},"margin_tablet":{"unit":"%","top":"","right":"","bottom":"","left":"","isLinked":true},"margin_mobile":{"unit":"%","top":"","right":"","bottom":"","left":"","isLinked":true},"padding":{"unit":"%","top":"12","right":"8","bottom":"12","left":"8","isLinked":false},"padding_tablet":{"unit":"%","top":"20","right":"8","bottom":"20","left":"8","isLinked":false},"padding_mobile":{"unit":"%","top":"30","right":"6","bottom":"30","left":"6","isLinked":false},"background_background":"classic","__globals__":{"background_color":""},"_title":"My Account","flex_direction":"column","flex_align_items":"stretch","flex_gap":{"size":10,"unit":"px"},"content_width":"full","background_image":{"url":"","id":""},"background_video_fallback":{"url":"","id":""},"background_slideshow_gallery":[],"background_hover_image":{"url":"","id":""},"background_hover_video_fallback":{"url":"","id":""},"background_hover_slideshow_gallery":[],"background_overlay_image":{"url":"","id":""},"background_overlay_video_fallback":{"url":"","id":""},"background_overlay_slideshow_gallery":[],"background_overlay_hover_image":{"url":"","id":""},"background_overlay_hover_video_fallback":{"url":"","id":""},"background_overlay_hover_slideshow_gallery":[]},"elements":[{"id":"262c7a","settings":{"tabs":[{"field_key":"dashboard","field_label":"Dashboard","tab_name":"Dashboard","_id":"c37de9a"},{"field_key":"orders","field_label":"Orders","tab_name":"Orders","_id":"5b20fdc"},{"field_key":"downloads","field_label":"Downloads","tab_name":"Downloads","_id":"0f39572"},{"field_key":"edit-address","field_label":"Addresses","tab_name":"Addresses","_id":"c47e312"},{"field_key":"edit-account","field_label":"Account Details","tab_name":"Account Details","_id":"d971dc2"},{"field_key":"customer-logout","field_label":"Logout","tab_name":"Logout","_id":"9b335b0"}],"tabs_typography_typography":"custom","tabs_typography_font_family":"Poppins","tabs_typography_font_size":{"unit":"px","size":16,"sizes":[]},"tabs_typography_font_size_tablet":{"unit":"px","size":14,"sizes":[]},"tabs_typography_font_weight":"400","tabs_typography_text_transform":"capitalize","tabs_typography_font_style":"normal","tabs_typography_text_decoration":"none","tabs_typography_line_height":{"unit":"em","size":1,"sizes":[]},"tabs_typography_letter_spacing":{"unit":"px","size":0,"sizes":[]},"tabs_normal_background_background":"classic","tabs_normal_background_color":"#F3F5F8","tabs_normal_color":"#324A6D","tabs_hover_background_background":"classic","tabs_hover_background_color":"#F9FAFD","tabs_hover_color":"#467FF7","tabs_active_background_background":"classic","tabs_active_background_color":"#F9FAFD","tabs_active_color":"#467FF7","tabs_border_type":"none","sections_border_type":"solid","sections_border_width":{"unit":"px","top":"1","right":"1","bottom":"1","left":"1","isLinked":true},"sections_border_color":"#F3F5F8","sections_border_radius":{"unit":"px","top":"0","right":"0","bottom":"0","left":"0","isLinked":true},"typography_section_titles_color":"#1C244B","section_titles_typography_typography":"custom","section_titles_typography_font_family":"Poppins","section_titles_typography_font_size":{"unit":"px","size":22,"sizes":[]},"section_titles_typography_font_size_mobile":{"unit":"px","size":18,"sizes":[]},"section_titles_typography_font_weight":"600","section_titles_typography_text_transform":"capitalize","section_titles_typography_font_style":"normal","section_titles_typography_text_decoration":"none","section_titles_typography_line_height":{"unit":"em","size":1.2,"sizes":[]},"section_titles_typography_letter_spacing":{"unit":"px","size":0,"sizes":[]},"section_titles_typography_word_spacing":{"unit":"em","size":"","sizes":[]},"section_title_spacing":{"unit":"px","size":20,"sizes":[]},"general_text_color":"#324A6D","general_text_typography_typography":"custom","general_text_typography_font_family":"Poppins","general_text_typography_font_size":{"unit":"px","size":16,"sizes":[]},"general_text_typography_font_size_tablet":{"unit":"px","size":14,"sizes":[]},"general_text_typography_font_weight":"300","general_text_typography_text_transform":"none","general_text_typography_font_style":"normal","general_text_typography_text_decoration":"none","general_text_typography_line_height":{"unit":"em","size":1.5,"sizes":[]},"general_text_typography_letter_spacing":{"unit":"px","size":0,"sizes":[]},"login_messages_typography_typography":"custom","login_messages_typography_font_family":"Poppins","login_messages_typography_font_size":{"unit":"px","size":16,"sizes":[]},"login_messages_typography_font_size_tablet":{"unit":"px","size":14,"sizes":[]},"login_messages_typography_font_weight":"300","login_messages_typography_text_transform":"none","login_messages_typography_font_style":"normal","login_messages_typography_text_decoration":"none","login_messages_typography_line_height":{"unit":"em","size":1.5,"sizes":[]},"login_messages_typography_letter_spacing":{"unit":"px","size":0,"sizes":[]},"forms_rows_gap":{"unit":"px","size":15,"sizes":[],"px":0},"forms_fields_normal_background_background":"classic","forms_fields_border_border":"solid","forms_fields_border_width":{"unit":"px","top":"1","right":"1","bottom":"1","left":"1","isLinked":true},"forms_fields_border_radius":{"unit":"px","top":"0","right":"0","bottom":"0","left":"0","isLinked":false},"forms_buttons_background_background":"classic","forms_buttons_hover_background_background":"classic","forms_buttons_border_border":"solid","forms_buttons_border_width":{"unit":"px","top":"1","right":"1","bottom":"1","left":"1","isLinked":true},"forms_buttons_border_radius":{"unit":"px","top":"300","right":"300","bottom":"300","left":"300","isLinked":true},"__globals__":{"tabs_typography_typography":"globals\/typography?id=accent","tabs_normal_background_color":"globals\/colors?id=secondary","tabs_normal_color":"globals\/colors?id=text","tabs_hover_color":"globals\/colors?id=accent","tabs_active_color":"globals\/colors?id=accent","tabs_active_background_color":"globals\/colors?id=764183d","tabs_hover_background_color":"globals\/colors?id=764183d","sections_border_color":"globals\/colors?id=secondary","typography_section_titles_color":"globals\/colors?id=primary","section_titles_typography_typography":"globals\/typography?id=392b9e0","general_text_color":"globals\/colors?id=text","general_text_typography_typography":"globals\/typography?id=text","login_messages_typography_typography":"globals\/typography?id=text","login_messages_color":"","checkboxes_typography_typography":"globals\/typography?id=text","checkboxes_color":"globals\/colors?id=text","payment_methods_radio_buttons_color":"globals\/colors?id=text","payment_methods_radio_buttons_typography_typography":"globals\/typography?id=text","links_normal_color":"globals\/colors?id=accent","links_hover_color":"globals\/colors?id=primary","forms_label_color":"globals\/colors?id=text","forms_label_typography_typography":"globals\/typography?id=text","forms_field_typography_typography":"globals\/typography?id=text","forms_fields_normal_color":"globals\/colors?id=text","forms_fields_normal_background_color":"globals\/colors?id=86b4fcd","forms_fields_border_color":"globals\/colors?id=text","forms_button_typography_typography":"globals\/typography?id=accent","forms_buttons_normal_text_color":"globals\/colors?id=d6cea4e","forms_buttons_background_color":"globals\/colors?id=accent","forms_buttons_border_color":"globals\/colors?id=accent","forms_buttons_hover_text_color":"globals\/colors?id=accent","forms_buttons_hover_background_color":"globals\/colors?id=86b4fcd","forms_buttons_hover_border_color":"globals\/colors?id=accent","tables_title_color":"globals\/colors?id=primary","tables_titles_typography_typography":"globals\/typography?id=6558fb1","tables_items_color":"globals\/colors?id=text","tables_items_typography_typography":"globals\/typography?id=text","variations_color":"globals\/colors?id=text","variations_typography_typography":"globals\/typography?id=text","tables_links_normal_color":"globals\/colors?id=accent","tables_links_hover_color":"globals\/colors?id=primary","tables_divider_border_color":"globals\/colors?id=14ef391","tables_button_typography_typography":"globals\/typography?id=accent","tables_button_normal_text_color":"globals\/colors?id=accent","tables_button_normal_background_color":"globals\/colors?id=86b4fcd","tables_button_border_color":"globals\/colors?id=accent","tables_button_hover_text_color":"globals\/colors?id=d6cea4e","tables_button_hover_background_color":"globals\/colors?id=accent","tables_button_hover_border_color":"globals\/colors?id=accent"},"tables_button_normal_background_background":"classic","tables_button_hover_background_background":"classic","tables_button_border_type":"solid","tables_button_border_width":{"unit":"px","top":"1","right":"1","bottom":"1","left":"1","isLinked":true},"tables_button_border_radius":{"unit":"px","top":"300","right":"300","bottom":"300","left":"300","isLinked":true},"tabs_padding":{"unit":"%","top":"6","right":"5","bottom":"6","left":"5","isLinked":false},"tabs_padding_tablet":{"unit":"%","top":"","right":"","bottom":"","left":"","isLinked":true},"tabs_padding_mobile":{"unit":"%","top":"","right":"","bottom":"","left":"","isLinked":true},"sections_padding":{"unit":"px","top":"10","right":"10","bottom":"10","left":"10","isLinked":true},"tabs_normal_background_image":{"url":"","id":""},"tabs_normal_background_video_fallback":{"url":"","id":""},"tabs_normal_background_slideshow_gallery":[],"tabs_hover_background_image":{"url":"","id":""},"tabs_hover_background_video_fallback":{"url":"","id":""},"tabs_hover_background_slideshow_gallery":[],"tabs_active_background_image":{"url":"","id":""},"tabs_active_background_video_fallback":{"url":"","id":""},"tabs_active_background_slideshow_gallery":[],"forms_fields_normal_background_image":{"url":"","id":""},"forms_fields_normal_background_video_fallback":{"url":"","id":""},"forms_fields_normal_background_slideshow_gallery":[],"forms_fields_focus_background_image":{"url":"","id":""},"forms_fields_focus_background_video_fallback":{"url":"","id":""},"forms_fields_focus_background_slideshow_gallery":[],"forms_buttons_background_image":{"url":"","id":""},"forms_buttons_background_video_fallback":{"url":"","id":""},"forms_buttons_background_slideshow_gallery":[],"forms_buttons_hover_background_image":{"url":"","id":""},"forms_buttons_hover_background_video_fallback":{"url":"","id":""},"forms_buttons_hover_background_slideshow_gallery":[],"tables_button_normal_background_image":{"url":"","id":""},"tables_button_normal_background_video_fallback":{"url":"","id":""},"tables_button_normal_background_slideshow_gallery":[],"tables_button_hover_background_image":{"url":"","id":""},"tables_button_hover_background_video_fallback":{"url":"","id":""},"tables_button_hover_background_slideshow_gallery":[],"_background_image":{"url":"","id":""},"_background_video_fallback":{"url":"","id":""},"_background_slideshow_gallery":[],"_background_hover_image":{"url":"","id":""},"_background_hover_video_fallback":{"url":"","id":""},"_background_hover_slideshow_gallery":[],"_mask_image":{"url":"","id":""}},"elements":[],"isInner":false,"widgetType":"woocommerce-my-account","elType":"widget"}],"isInner":false,"elType":"container"}],"settings":{"template":"elementor_header_footer"},"metadata":[]}